skmatter/__init__.py
skmatter/_selection.py
skmatter/_version.py
skmatter/clustering/__init__.py
skmatter/clustering/_quick_shift.py
skmatter/datasets/__init__.py
skmatter/datasets/_base.py
skmatter/datasets/data/beran_roy_properties.npz
skmatter/datasets/data/csd-1000r.npz
skmatter/datasets/data/degenerate_CH4_manifold.npz
skmatter/datasets/data/h2o-blyp-piglet.npz
skmatter/datasets/data/nice_dataset.npz
skmatter/datasets/data/who_dataset.csv
skmatter/datasets/descr/csd-1000r.rst
skmatter/datasets/descr/degenerate_CH4_manifold.rst
skmatter/datasets/descr/h2o-blyp-piglet.rst
skmatter/datasets/descr/nice_dataset.rst
skmatter/datasets/descr/who_dataset.rst
skmatter/decomposition/__init__.py
skmatter/decomposition/_kernel_pcovc.py
skmatter/decomposition/_kernel_pcovr.py
skmatter/decomposition/_kpcov.py
skmatter/decomposition/_pcov.py
skmatter/decomposition/_pcovc.py
skmatter/decomposition/_pcovr.py
skmatter/feature_selection/__init__.py
skmatter/feature_selection/_base.py
skmatter/linear_model/__init__.py
skmatter/linear_model/_base.py
skmatter/linear_model/_ridge.py
skmatter/metrics/__init__.py
skmatter/metrics/_pairwise.py
skmatter/metrics/_prediction_rigidities.py
skmatter/metrics/_reconstruction_measures.py
skmatter/model_selection/__init__.py
skmatter/model_selection/_split.py
skmatter/neighbors/__init__.py
skmatter/neighbors/_sparsekde.py
skmatter/preprocessing/__init__.py
skmatter/preprocessing/_data.py
skmatter/sample_selection/__init__.py
skmatter/sample_selection/_base.py
skmatter/sample_selection/_voronoi_fps.py
skmatter/utils/__init__.py
skmatter/utils/_orthogonalizers.py
skmatter/utils/_pcovc_utils.py
skmatter/utils/_pcovr_utils.py
skmatter/utils/_progress_bar.py
skmatter/utils/_sparsekde.py
skmatter-0.3.3.dist-info/licenses/LICENSE
skmatter-0.3.3.dist-info/METADATA
skmatter-0.3.3.dist-info/WHEEL
skmatter-0.3.3.dist-info/top_level.txt
skmatter-0.3.3.dist-info/RECORD
