Metadata-Version: 2.4
Name: skmatter
Version: 0.3.3
Summary: A collection of scikit-learn compatible utilities that implement methods born out of the materials science and chemistry communities.
Author: Guillaume Fraux, Sergei Kliavinek, Alexander Goscinski, Benjamin A. Helfrecht, Victor P. Principe, Philip Loche, Michele Ceriotti
Author-email: "Rose K. Cersonsky" <rose.cersonsky@wisc.edu>
License: BSD-3-Clause
Project-URL: homepage, http://scikit-matter.readthedocs.io
Project-URL: documentation, http://scikit-matter.readthedocs.io
Project-URL: repository, https://github.com/scikit-learn-contrib/scikit-matter
Project-URL: issues, https://github.com/scikit-learn-contrib/scikit-matterissues
Project-URL: changelog, http://scikit-matter.readthedocs.io/en/latest/changelog.html
Classifier: Development Status :: 4 - Beta
Classifier: Environment :: Console
Classifier: Intended Audience :: Science/Research
Classifier: License :: OSI Approved :: BSD License
Classifier: Natural Language :: English
Classifier: Operating System :: POSIX
Classifier: Operating System :: MacOS :: MacOS X
Classifier: Operating System :: Microsoft :: Windows
Classifier: Programming Language :: Python :: 3
Classifier: Programming Language :: Python :: 3.11
Classifier: Programming Language :: Python :: 3.12
Classifier: Programming Language :: Python :: 3.13
Classifier: Programming Language :: Python :: 3.14
Classifier: Topic :: Scientific/Engineering
Requires-Python: >=3.11
License-File: LICENSE
Requires-Dist: scikit-learn<1.9,>=1.8
Requires-Dist: scipy>=1.15
Provides-Extra: examples
Requires-Dist: matplotlib; extra == "examples"
Requires-Dist: pandas; extra == "examples"
Requires-Dist: tqdm; extra == "examples"
Dynamic: license-file
